multiverse/__init__.py
multiverse/admin.py
multiverse/apps.py
multiverse/awareness.py
multiverse/db/__init__.py
multiverse/db/backends/__init__.py
multiverse/db/backends/postgresql/__init__.py
multiverse/db/backends/postgresql/utils.py
multiverse/db/backends/sqlite3/__init__.py
multiverse/db/backends/sqlite3/utils.py
multiverse/db/backends/utils.py
multiverse/db/router.py
multiverse/management/__init__.py
multiverse/management/commands/__init__.py
multiverse/management/commands/create_tenant.py
multiverse/management/commands/destroy_tenant.py
multiverse/middleware.py
multiverse/migrations/0001_initial.py
multiverse/migrations/__init__.py
multiverse/models.py
multiverse/signals.py
multiverse/tasks/__init__.py
multiverse/tasks/django_q.py
multiverse/test/__init__.py
multiverse/test/cases.py
multiverse/test/client.py
multiverse/test/drf/__init__.py
multiverse/test/drf/cases.py
multiverse/test/drf/client.py
multiverse/test/utls.py
multiverse/utils.py
django_multiverse-1.0.9.dist-info/LICENSE
django_multiverse-1.0.9.dist-info/METADATA
django_multiverse-1.0.9.dist-info/WHEEL
django_multiverse-1.0.9.dist-info/RECORD
