Metadata-Version: 2.1
Name: django-multiverse
Version: 1.0.9
Summary: Django Multiverse: Multi-Tenancy for Django
Home-page: https://github.com/dmp593/django-multiverse
License: MIT
Keywords: Django,Multiverse,Multi-Tenancy,Tenants
Author: Daniel Pinto
Author-email: dmp593@gmail.com
Requires-Python: >=3.10,<4.0
Classifier: Environment :: Web Environment
Classifier: Framework :: Django
Classifier: Framework :: Django :: 4.0
Classifier: Framework :: Django :: 4.1
Classifier: Framework :: Django :: 4.2
Classifier: Framework :: Django :: 5.0
Classifier: Framework :: Django :: 5.1
Classifier: Intended Audience :: Developers
Classifier: License :: OSI Approved :: MIT License
Classifier: Operating System :: OS Independent
Classifier: Programming Language :: Python
Classifier: Programming Language :: Python :: 3
Classifier: Programming Language :: Python :: 3.10
Classifier: Programming Language :: Python :: 3.11
Classifier: Programming Language :: Python :: 3.12
Classifier: Programming Language :: Python :: 3.13
Classifier: Programming Language :: Python :: 3 :: Only
Classifier: Topic :: Software Development :: Libraries
Classifier: Topic :: Software Development :: Libraries :: Application Frameworks
Provides-Extra: all
Provides-Extra: django-q2
Provides-Extra: drf
Provides-Extra: postgres
Requires-Dist: Django (>=5.0,<6.0)
Requires-Dist: django-q2 (>=1.6.2,<2.0.0) ; extra == "django-q2" or extra == "all"
Requires-Dist: djangorestframework (>=3.15,<4.0) ; extra == "drf" or extra == "all"
Requires-Dist: psycopg (>=3.2.1,<4.0.0) ; extra == "postgres" or extra == "all"
Project-URL: Repository, https://github.com/dmp593/django-multiverse
